MANIFEST.in
README.rst
redmine.py
setup.py
helga_redmine.egg-info/PKG-INFO
helga_redmine.egg-info/SOURCES.txt
helga_redmine.egg-info/dependency_links.txt
helga_redmine.egg-info/entry_points.txt
helga_redmine.egg-info/requires.txt
helga_redmine.egg-info/top_level.txt
tests/conftest.py
tests/test_redmine.py