Metadata-Version: 1.1
Name: helga-redmine
Version: 0.0.6
Summary: redmine plugin for helga
Home-page: https://github.com/alfredodeza/helga-redmine
Author: alfredo deza
Author-email: contact@deza.pe
License: MIT
Keywords: irc bot redmine
Platform: UNKNOWN
Classifier: Development Status :: 4 - Beta
Classifier: License :: OSI Approved :: MIT License
Classifier: Operating System :: OS Independent
Classifier: Programming Language :: Python
Classifier: Topic :: Software Development :: Libraries :: Python Modules
